tailslide/__init__.py
tailslide/flag_manager.py
tailslide/nats_client.py
tailslide/redis_timeseries_client.py
tailslide/toggler.py
tailslide_sdk-0.1.7.dist-info/LICENSE
tailslide_sdk-0.1.7.dist-info/METADATA
tailslide_sdk-0.1.7.dist-info/WHEEL
tailslide_sdk-0.1.7.dist-info/top_level.txt
tailslide_sdk-0.1.7.dist-info/RECORD
