Metadata-Version: 2.1
Name: tailslide-sdk
Version: 0.1.7
Summary: A example Python package
Home-page: https://github.com/shuds13/pyexample
Author: Steven Liou, Trent Cooper, Elaine Vuong, Jordan Eggers
Author-email: tailslide.io.2205@gmail.com 
License: MIT
Classifier: Development Status :: 1 - Planning
Classifier: Intended Audience :: Science/Research
Classifier: License :: OSI Approved :: BSD License
Classifier: Operating System :: POSIX :: Linux
Classifier: Programming Language :: Python :: 2
Classifier: Programming Language :: Python :: 2.7
Classifier: Programming Language :: Python :: 3
Classifier: Programming Language :: Python :: 3.4
Classifier: Programming Language :: Python :: 3.5
License-File: LICENSE
Requires-Dist: nats-py (>=2.1.4)
Requires-Dist: redis (>=4.3.4)
